stfu_tg/__init__.py
stfu_tg/doc.py
stfu_tg/extras.py
stfu_tg/formatting.py
stfu_tg/formatting_extras.py
stfu_tg/md/__init__.py
stfu_tg/md/misc.py
stfu_tg/md/table.py
stfu_tg/sections.py
stfu_tg/special.py
stfu_tg/telegram.py
stfu_tg-3.4.dist-info/LICENSE.md
stfu_tg-3.4.dist-info/METADATA
stfu_tg-3.4.dist-info/WHEEL
stfu_tg-3.4.dist-info/RECORD
