Metadata-Version: 2.1
Name: stfu_tg
Version: 3.4
Summary: Sophie Text Formatting Utility
Home-page: https://gitlab.com/SophieBot/stf
Author: Yacha
Author-email: yacha@orangefox.tech
Requires-Python: >=3.9,<4.0
Classifier: License :: OSI Approved :: MIT License
Classifier: Operating System :: OS Independent
Classifier: Programming Language :: Python :: 3
Classifier: Programming Language :: Python :: 3.9
Classifier: Programming Language :: Python :: 3.10
Classifier: Programming Language :: Python :: 3.11
Classifier: Programming Language :: Python :: 3.12
Classifier: Programming Language :: Python :: 3.13
Provides-Extra: entities
Project-URL: Repository, https://gitlab.com/SophieBot/stf
